vision_browser_sdk/__init__.py
vision_browser_sdk/client.py
vision_browser_sdk/exceptions.py
vision_browser_sdk/models.py
vision_browser_sdk/services/_base.py
vision_browser_sdk/services/folders.py
vision_browser_sdk/services/profiles.py
vision_browser_sdk/services/proxies.py
vision_browser_sdk/services/statuses.py
vision_browser_sdk/services/tags.py
vision_browser_sdk-0.1.1.dist-info/METADATA
vision_browser_sdk-0.1.1.dist-info/WHEEL
vision_browser_sdk-0.1.1.dist-info/RECORD
