Metadata-Version: 2.4
Name: vision-browser-sdk
Version: 0.1.1
Summary: Modern, fully-typed, sync and async Python SDK for the Vision Browser API.
License: MIT
Keywords: vision,browser,api,sdk,async,httpx
Author: Landerix
Author-email: dimitrymasl@gmail.com
Requires-Python: >=3.9,<4.0
Classifier: License :: OSI Approved :: MIT License
Classifier: Programming Language :: Python :: 3
Classifier: Programming Language :: Python :: 3.9
Classifier: Programming Language :: Python :: 3.10
Classifier: Programming Language :: Python :: 3.11
Classifier: Programming Language :: Python :: 3.12
Classifier: Programming Language :: Python :: 3.13
Classifier: Programming Language :: Python :: 3.14
Requires-Dist: httpx (>=0.28.1,<0.29.0)
Requires-Dist: pydantic (>=2.12.1,<3.0.0)
Project-URL: Repository, https://github.com/dimitrymas/vision-browser-sdk
